aoptk/__init__.py
aoptk/chemical.py
aoptk/effect.py
aoptk/find_chemical.py
aoptk/regex_sentence_generator.py
aoptk/sentence.py
aoptk/sentence_generator.py
aoptk/spacy_processor.py
aoptk/abbreviations/__init__.py
aoptk/abbreviations/abbreviation_translator.py
aoptk/abbreviations/abbreviation_translator_dictionary.py
aoptk/abbreviations/abbreviation_translator_dictionary_generator.py
aoptk/application/__init__.py
aoptk/application/chemical_identifier.py
aoptk/application/publication_tracker.py
aoptk/cleaning/__init__.py
aoptk/cleaning/html_tag_remover.py
aoptk/cleaning/text_cleaner.py
aoptk/literature/__init__.py
aoptk/literature/abbreviations.py
aoptk/literature/abstract.py
aoptk/literature/get_abstract.py
aoptk/literature/get_id.py
aoptk/literature/get_pdf.py
aoptk/literature/get_publication.py
aoptk/literature/id.py
aoptk/literature/pdf.py
aoptk/literature/pdf_parser.py
aoptk/literature/publication.py
aoptk/literature/publication_metadata.py
aoptk/literature/pymupdf_parser.py
aoptk/literature/utils.py
aoptk/literature/databases/__init__.py
aoptk/literature/databases/europepmc.py
aoptk/literature/databases/pubmed.py
aoptk/normalization/__init__.py
aoptk/normalization/mesh_terms.py
aoptk/normalization/normalize_chemical.py
aoptk/normalization/provide_mesh_term_dataframe_from_xml.py
aoptk/normalization/provide_normalization_dataframe.py
aoptk/normalization/pubchem_abbreviation_short.py
aoptk/normalization/pubchem_abbreviation_uppercase.py
aoptk/normalization/pubchem_api.py
aoptk/normalization/pubchem_local.py
aoptk/relationships/__init__.py
aoptk/relationships/find_relationship.py
aoptk/relationships/relationship.py
aoptk/relationships/zero_shot_classification.py
aoptk/relationships/zero_shot_classification_multiple.py
aoptk/relationships/zero_shot_classification_single.py
aoptk-0.1.6.dist-info/licenses/LICENSE
aoptk-0.1.6.dist-info/METADATA
aoptk-0.1.6.dist-info/WHEEL
aoptk-0.1.6.dist-info/entry_points.txt
aoptk-0.1.6.dist-info/top_level.txt
aoptk-0.1.6.dist-info/RECORD
