Metadata-Version: 2.4
Name: aoptk
Version: 0.1.6
Summary: Tools to support data mining for the development of (q)AOPs
Author-email: Robin Durník <rdurnik@gmail.com>, Helge Hecht <helge.hecht@recetox.muni.cz>
License: MIT License
Project-URL: Repository, https://github.com/rdurnik/aoptk
Project-URL: Issues, https://github.com/rdurnik/aoptk/issues
Project-URL: ReadTheDocs, https://aoptk.readthedocs.io
Keywords: AOP, toxicology, data mining, ai, machine learning, data analysis
Classifier: Development Status :: 2 - Pre-Alpha
Classifier: Intended Audience :: Developers
Classifier: Intended Audience :: Science/Research
Classifier: Natural Language :: English
Classifier: Programming Language :: Python :: 3
Classifier: Programming Language :: Python :: 3.10
Classifier: Programming Language :: Python :: 3.11
Classifier: Programming Language :: Python :: 3.12
Requires-Python: >=3.10
License-File: LICENSE
Requires-Dist: pandas
Requires-Dist: pymupdf
Requires-Dist: metapub
Requires-Dist: requests
Requires-Dist: scispacy
Requires-Dist: spacy<3.8.0,>=3.0.0
Requires-Dist: beautifulsoup4
Requires-Dist: biopython
Requires-Dist: transformers
Requires-Dist: torch
Requires-Dist: openpyxl
Requires-Dist: click>=8.1
Provides-Extra: dev
Requires-Dist: build; extra == "dev"
Requires-Dist: bumpversion; extra == "dev"
Requires-Dist: coverage[toml]; extra == "dev"
Requires-Dist: pytest; extra == "dev"
Requires-Dist: pytest-cov; extra == "dev"
Requires-Dist: ruff; extra == "dev"
Requires-Dist: sphinx; extra == "dev"
Requires-Dist: sphinx_rtd_theme; extra == "dev"
Requires-Dist: sphinx-autoapi; extra == "dev"
Requires-Dist: myst_parser; extra == "dev"
Requires-Dist: jupyter; extra == "dev"
Requires-Dist: ipykernel; extra == "dev"
Provides-Extra: docs
Requires-Dist: sphinx; extra == "docs"
Requires-Dist: sphinx_rtd_theme; extra == "docs"
Requires-Dist: sphinx-autoapi; extra == "docs"
Requires-Dist: myst_parser; extra == "docs"
Provides-Extra: publishing
Requires-Dist: build; extra == "publishing"
Requires-Dist: twine; extra == "publishing"
Requires-Dist: wheel; extra == "publishing"
Dynamic: license-file
